Metadata-Version: 2.1
Name: tap-mongodb
Version: 3.3.0
Summary: Singer.io tap for extracting data from MongoDB
Home-page: https://singer.io
Author: Stitch
Classifier: Programming Language :: Python :: 3 :: Only
License-File: LICENSE
Requires-Dist: singer-python==6.3.0
Requires-Dist: pymongo==4.10.1
Requires-Dist: tzlocal==2.0.0
Provides-Extra: dev
Requires-Dist: pylint; extra == "dev"
Requires-Dist: nose2; extra == "dev"
Requires-Dist: ipdb; extra == "dev"
